{
  "category": "Resources",
  "crafting": [
    {
      "ingredients": [
        {
          "count": 1,
          "name": "Level"
        },
        {
          "count": 1,
          "name": "Cam"
        },
        {
          "count": 1,
          "name": "Bearing"
        }
      ],
      "station": "Module Fabricator",
      "time": 30
    }
  ],
  "name": "Fireproof Module",
  "translation": "Fireproof Module",
  "type": "FireproofBoost_C",
  "weight": 0.24,
  "moduleInfo": {
    "max": 20,
    "increase": 4.5,
    "maxIncrease": 90
  },
  "drops": [
    {
      "location": "Modules_T1",
      "chance": 5.263158,
      "minQuantity": 1,
      "maxQuantity": 1
    }
  ]
}