{
  "name": "Nomad Cloth",
  "parent": "Advanced Fiberworking Station",
  "type": "BasicCloth_C",
  "category": "Resources",
  "crafting": [
    {
      "ingredients": [
        {
          "count": 50,
          "name": "Cattail"
        },
        {
          "count": 1,
          "name": "Bone Glue"
        }
      ],
      "station": "Advanced Fiberworking Station",
      "time": 60
    },
    {
      "ingredients": [
        {
          "count": 50,
          "name": "Cattail"
        },
        {
          "count": 1,
          "name": "Bone Glue"
        }
      ],
      "station": "Artisan Fiberworking Station",
      "time": 60
    },
    {
      "ingredients": [
        {
          "count": 12,
          "name": "Cotton"
        },
        {
          "count": 6,
          "name": "Earth Wax"
        }
      ],
      "station": "Advanced Fiberworking Station",
      "time": 16
    },
    {
      "ingredients": [
        {
          "count": 12,
          "name": "Cotton"
        },
        {
          "count": 6,
          "name": "Earth Wax"
        }
      ],
      "station": "Artisan Fiberworking Station",
      "time": 16
    }
  ],
  "trade_price": 28,
  "translation": "Nomad Cloth",
  "experiencieReward": 65,
  "stackSize": 100,
  "weight": 0.24
}